main.py
src/__init__.py
src/server.py
src/tools/keep/__init__.py
src/tools/keep/keep.py
src/tools/new_open/__init__.py
src/tools/new_open/new_open.py
src/utils/logger/__init__.py
src/utils/logger/logger.py
tdsaas_mcp-0.1.2.dist-info/METADATA
tdsaas_mcp-0.1.2.dist-info/WHEEL
tdsaas_mcp-0.1.2.dist-info/entry_points.txt
tdsaas_mcp-0.1.2.dist-info/top_level.txt
tdsaas_mcp-0.1.2.dist-info/RECORD
